dschloe_dl_framework/__init__.py
dschloe_dl_framework/step10.py
dschloe_dl_framework-0.0.1.dist-info/METADATA
dschloe_dl_framework-0.0.1.dist-info/WHEEL
dschloe_dl_framework-0.0.1.dist-info/top_level.txt
dschloe_dl_framework-0.0.1.dist-info/RECORD
