Metadata-Version: 2.1
Name: dschloe-dl-framework
Version: 0.0.1
Summary: Deep Neural Networks built from the book `Deep Learning from Scratch`
Home-page: https://github.com/dschloe/dl_framework
Author: DSChloe
Author-email: jhjung@dschloe.com
License: MIT
Keywords: Deep Learning
Platform: UNKNOWN
Classifier: Programming Language :: Python :: 2.7
Classifier: Programming Language :: Python :: 3
Classifier: Programming Language :: Python :: 3.8
